alphaj_krx_crawler/__init__.py
alphaj_krx_crawler-0.1.1.dist-info/METADATA
alphaj_krx_crawler-0.1.1.dist-info/WHEEL
alphaj_krx_crawler-0.1.1.dist-info/top_level.txt
alphaj_krx_crawler-0.1.1.dist-info/RECORD
