Metadata-Version: 2.1
Name: alphaj-krx-crawler
Version: 0.1.1
Summary: A KRX Cralwer
Home-page: https://bitbucket.org/jaeminyx/krxcrawler/src
Author: Alpha J
Author-email: jaeminyx@gmail.com
License: UNKNOWN
Platform: UNKNOWN
Classifier: Programming Language :: Python :: 3
Classifier: License :: OSI Approved :: MIT License
Classifier: Operating System :: OS Independent
Requires-Dist: requests
